python_pdb/__init__.py
python_pdb/aligners.py
python_pdb/chemistry.py
python_pdb/comparisons.py
python_pdb/entities.py
python_pdb/parsers.py
python_pdb/records.py
python_pdb/formats/__init__.py
python_pdb/formats/pandas.py
python_pdb/formats/pdb.py
python_pdb/formats/residue.py
python_pdb-0.1.3.dist-info/LICENSE
python_pdb-0.1.3.dist-info/METADATA
python_pdb-0.1.3.dist-info/WHEEL
python_pdb-0.1.3.dist-info/top_level.txt
python_pdb-0.1.3.dist-info/RECORD
