Metadata-Version: 2.1
Name: python_pdb
Version: 0.1.3
Summary: Tools for working with Protein Data Bank Files
Author-email: Benjamin McMaster <benjamin.mcmaster@rdm.ox.ac.uk>
Requires-Python: >=3.10
License-File: LICENSE
Requires-Dist: numpy
Requires-Dist: pandas
Provides-Extra: develop
Requires-Dist: flake8 ; extra == 'develop'
Requires-Dist: Flake8-pyproject ; extra == 'develop'
Requires-Dist: isort ; extra == 'develop'
Requires-Dist: myst-parser ; extra == 'develop'
Requires-Dist: nbsphinx ; extra == 'develop'
Requires-Dist: pytest ; extra == 'develop'
Requires-Dist: prysk[pytest-plugin] ; extra == 'develop'
Requires-Dist: python-semantic-release ; extra == 'develop'
Requires-Dist: sphinx ; extra == 'develop'
Requires-Dist: sphinx-rtd-theme ; extra == 'develop'
